minion/__init__.py
minion/_compat.py
minion/cli.py
minion/const.py
minion/logs.py
minion/actions/action_node.py
minion/actions/lmp_action_node.py
minion/agents/__init__.py
minion/agents/base_agent.py
minion/agents/conversational_agent.py
minion/configs/config.py
minion/main/__init__.py
minion/main/async_stats_tracker.py
minion/main/brain.py
minion/main/check.py
minion/main/check_route.py
minion/main/compare_result.py
minion/main/ic_env.py
minion/main/improve.py
minion/main/improve_route.py
minion/main/input.py
minion/main/ldb_worker.py
minion/main/lmp.py
minion/main/local_python_env.py
minion/main/minion.py
minion/main/pre_processing.py
minion/main/preprocessing.py
minion/main/prompt.py
minion/main/python_env.py
minion/main/result_strategy.py
minion/main/rpyc_python_env.py
minion/main/save_plan.py
minion/main/symbol_table.py
minion/main/task_graph.py
minion/main/worker.py
minion/models/schemas.py
minion/providers/__init__.py
minion/providers/azure_inference_provider.py
minion/providers/azure_provider.py
minion/providers/base_provider.py
minion/providers/cost.py
minion/providers/litellm_provider.py
minion/providers/llm_provider_registry.py
minion/providers/openai_provider.py
minion/schema/__init__.py
minion/schema/message_types.py
minion/schema/messages.py
minion/tools/__init__.py
minion/tools/base_tool.py
minion/tools/default_tools.py
minion/utils/answer_extraction.py
minion/utils/custom_decoder.py
minion/utils/model_price.py
minion/utils/model_prices_and_context_window.json
minion/utils/process.py
minion/utils/sanitize.py
minion/utils/syncheck.py
minion/utils/template.py
minion/utils/token_counter.py
minion/utils/utils.py
minionx-0.1.3.dist-info/METADATA
minionx-0.1.3.dist-info/WHEEL
minionx-0.1.3.dist-info/entry_points.txt
minionx-0.1.3.dist-info/licenses/LICENSE
minionx-0.1.3.dist-info/RECORD
