Metadata-Version: 2.4
Name: minionx
Version: 0.1.3
Summary: 👷‍♂️Minion is Agent's Brain. Minion is designed to execute any type of queries, offering a variety of features that demonstrate its flexibility and intelligence.
Project-URL: Homepage, https://github.com/femto/minion
Project-URL: Repository, https://github.com/femto/minion.git
Author-email: femto <femtowin@gmail.com>
License-Expression: MIT
License-File: LICENSE
Keywords: agent,ai,automation,framework,llm
Classifier: Development Status :: 3 - Alpha
Classifier: Intended Audience :: Developers
Classifier: Programming Language :: Python :: 3
Classifier: Programming Language :: Python :: 3.8
Classifier: Programming Language :: Python :: 3.9
Classifier: Programming Language :: Python :: 3.10
Classifier: Programming Language :: Python :: 3.11
Requires-Python: >=3.8
Requires-Dist: accelerate
Requires-Dist: aiofiles
Requires-Dist: aiosqlite
Requires-Dist: antlr4-python3-runtime
Requires-Dist: astor
Requires-Dist: astroid
Requires-Dist: astunparse
Requires-Dist: asyncpg
Requires-Dist: azure-ai-inference
Requires-Dist: azure-identity
Requires-Dist: colorama
Requires-Dist: datasets
Requires-Dist: dill
Requires-Dist: ell-ai
Requires-Dist: graphviz
Requires-Dist: intercode-bench
Requires-Dist: jinja2
Requires-Dist: jsonlines>=3.1.0
Requires-Dist: litellm
Requires-Dist: loguru
Requires-Dist: matplotlib
Requires-Dist: mem0ai
Requires-Dist: nltk
Requires-Dist: ollama
Requires-Dist: optillm
Requires-Dist: pysnooper
Requires-Dist: python-dotenv
Requires-Dist: rpyc
Requires-Dist: sqlalchemy
Requires-Dist: sqlmodel
Requires-Dist: tenacity
Requires-Dist: tree-sitter
Requires-Dist: tree-sitter-python
Provides-Extra: all
Requires-Dist: black; extra == 'all'
Requires-Dist: google-adk; extra == 'all'
Requires-Dist: litellm; extra == 'all'
Requires-Dist: pytest; extra == 'all'
Requires-Dist: pytest-asyncio; extra == 'all'
Requires-Dist: ruff; extra == 'all'
Provides-Extra: dev
Requires-Dist: black; extra == 'dev'
Requires-Dist: pytest; extra == 'dev'
Requires-Dist: pytest-asyncio; extra == 'dev'
Requires-Dist: ruff; extra == 'dev'
Provides-Extra: google
Requires-Dist: google-adk; extra == 'google'
Requires-Dist: litellm; extra == 'google'
